README.rst
setup.py
jaeum_modifier/__init__.py
jaeum_modifier/api.py
jaeum_modifier/exceptions.py
jaeum_modifier/internals.py
jaeum_modifier/utils.py
jaeum_modifier.egg-info/PKG-INFO
jaeum_modifier.egg-info/SOURCES.txt
jaeum_modifier.egg-info/dependency_links.txt
jaeum_modifier.egg-info/requires.txt
jaeum_modifier.egg-info/top_level.txt
jaeum_modifier/tests/__init__.py
jaeum_modifier/tests/tests.py