Metadata-Version: 1.1
Name: jaeum-modifier
Version: 0.0.1a0
Summary: Hangul Jaeum Modifier
Home-page: https://github.com/hyunchel/jaeum-modifier
Author: Hyunchel Kim
Author-email: hyunchel.inbox@gmail.com
License: MIT
Keywords: language hangul jaeum modify
Platform: UNKNOWN
Classifier: Development Status :: 1 - Planning
Classifier: Intended Audience :: Developers
Classifier: Topic :: Software Development :: Libraries
Classifier: Topic :: Text Processing :: Linguistic
Classifier: License :: OSI Approved :: MIT License
Classifier: Programming Language :: Python :: 2.7
Classifier: Programming Language :: Python :: 2 :: Only
